{"name":"maou_short_14_shining_star","maxBlock":4,"BPM":180,"offset":45,"notes":[{"LPB":4,"num":9,"block":0,"type":1,"notes":[]},{"LPB":4,"num":27,"block":3,"type":1,"notes":[]},{"LPB":4,"num":46,"block":1,"type":1,"notes":[]},{"LPB":4,"num":64,"block":2,"type":1,"notes":[]},{"LPB":4,"num":82,"block":1,"type":1,"notes":[]},{"LPB":4,"num":82,"block":3,"type":1,"notes":[]},{"LPB":4,"num":98,"block":0,"type":1,"notes":[]},{"LPB":4,"num":98,"block":2,"type":1,"notes":[]},{"LPB":4,"num":103,"block":1,"type":1,"notes":[]},{"LPB":4,"num":103,"block":3,"type":1,"notes":[]},{"LPB":4,"num":107,"block":0,"type":1,"notes":[]},{"LPB":4,"num":107,"block":3,"type":1,"notes":[]},{"LPB":4,"num":118,"block":1,"type":1,"notes":[]},{"LPB":4,"num":127,"block":2,"type":1,"notes":[]},{"LPB":4,"num":137,"block":0,"type":1,"notes":[]},{"LPB":4,"num":144,"block":0,"type":1,"notes":[]},{"LPB":4,"num":155,"block":3,"type":1,"notes":[]},{"LPB":4,"num":162,"block":2,"type":1,"notes":[]},{"LPB":4,"num":171,"block":1,"type":1,"notes":[]},{"LPB":4,"num":178,"block":0,"type":1,"notes":[]},{"LPB":4,"num":192,"block":0,"type":1,"notes":[]},{"LPB":4,"num":201,"block":3,"type":1,"notes":[]},{"LPB":4,"num":210,"block":1,"type":1,"notes":[]},{"LPB":4,"num":210,"block":3,"type":1,"notes":[]},{"LPB":4,"num":217,"block":0,"type":1,"notes":[]},{"LPB":4,"num":217,"block":2,"type":1,"notes":[]},{"LPB":4,"num":228,"block":1,"type":1,"notes":[]},{"LPB":4,"num":235,"block":2,"type":1,"notes":[]},{"LPB":4,"num":244,"block":3,"type":1,"notes":[]},{"LPB":4,"num":244,"block":0,"type":1,"notes":[]},{"LPB":4,"num":248,"block":1,"type":1,"notes":[]},{"LPB":4,"num":248,"block":2,"type":1,"notes":[]},{"LPB":4,"num":253,"block":0,"type":1,"notes":[]},{"LPB":4,"num":253,"block":3,"type":1,"notes":[]},{"LPB":4,"num":255,"block":0,"type":1,"notes":[]},{"LPB":4,"num":255,"block":3,"type":1,"notes":[]},{"LPB":4,"num":265,"block":0,"type":1,"notes":[]},{"LPB":4,"num":274,"block":0,"type":1,"notes":[]},{"LPB":4,"num":283,"block":1,"type":1,"notes":[]},{"LPB":4,"num":292,"block":2,"type":1,"notes":[]},{"LPB":4,"num":301,"block":3,"type":1,"notes":[]},{"LPB":4,"num":310,"block":3,"type":1,"notes":[]},{"LPB":4,"num":319,"block":2,"type":1,"notes":[]},{"LPB":4,"num":329,"block":1,"type":1,"notes":[]},{"LPB":4,"num":338,"block":0,"type":1,"notes":[]},{"LPB":4,"num":347,"block":2,"type":1,"notes":[]},{"LPB":4,"num":356,"block":1,"type":1,"notes":[]},{"LPB":4,"num":365,"block":3,"type":1,"notes":[]},{"LPB":4,"num":374,"block":1,"type":1,"notes":[]},{"LPB":4,"num":383,"block":2,"type":1,"notes":[]},{"LPB":4,"num":394,"block":2,"type":1,"notes":[]},{"LPB":4,"num":394,"block":0,"type":1,"notes":[]},{"LPB":4,"num":396,"block":1,"type":1,"notes":[]},{"LPB":4,"num":396,"block":3,"type":1,"notes":[]},{"LPB":4,"num":401,"block":1,"type":1,"notes":[]},{"LPB":4,"num":401,"block":3,"type":1,"notes":[]},{"LPB":4,"num":403,"block":0,"type":1,"notes":[]},{"LPB":4,"num":403,"block":2,"type":1,"notes":[]},{"LPB":4,"num":408,"block":0,"type":1,"notes":[]},{"LPB":4,"num":408,"block":3,"type":1,"notes":[]},{"LPB":4,"num":410,"block":1,"type":1,"notes":[]},{"LPB":4,"num":410,"block":2,"type":1,"notes":[]},{"LPB":4,"num":415,"block":1,"type":1,"notes":[]},{"LPB":4,"num":415,"block":0,"type":1,"notes":[]},{"LPB":4,"num":415,"block":3,"type":1,"notes":[]},{"LPB":4,"num":417,"block":2,"type":1,"notes":[]},{"LPB":4,"num":417,"block":0,"type":1,"notes":[]},{"LPB":4,"num":417,"block":3,"type":1,"notes":[]},{"LPB":4,"num":429,"block":0,"type":1,"notes":[]},{"LPB":4,"num":429,"block":1,"type":1,"notes":[]},{"LPB":4,"num":435,"block":1,"type":1,"notes":[]},{"LPB":4,"num":435,"block":2,"type":1,"notes":[]},{"LPB":4,"num":445,"block":2,"type":1,"notes":[]},{"LPB":4,"num":445,"block":3,"type":1,"notes":[]},{"LPB":4,"num":451,"block":0,"type":1,"notes":[]},{"LPB":4,"num":451,"block":3,"type":1,"notes":[]},{"LPB":4,"num":464,"block":1,"type":1,"notes":[]},{"LPB":4,"num":469,"block":3,"type":1,"notes":[]},{"LPB":4,"num":469,"block":0,"type":1,"notes":[]},{"LPB":4,"num":471,"block":0,"type":1,"notes":[]},{"LPB":4,"num":471,"block":3,"type":1,"notes":[]},{"LPB":4,"num":481,"block":0,"type":1,"notes":[]},{"LPB":4,"num":481,"block":1,"type":1,"notes":[]},{"LPB":4,"num":481,"block":3,"type":1,"notes":[]},{"LPB":4,"num":490,"block":0,"type":1,"notes":[]},{"LPB":4,"num":490,"block":2,"type":1,"notes":[]},{"LPB":4,"num":490,"block":3,"type":1,"notes":[]},{"LPB":4,"num":501,"block":3,"type":1,"notes":[]},{"LPB":4,"num":509,"block":2,"type":1,"notes":[]},{"LPB":4,"num":519,"block":1,"type":1,"notes":[]},{"LPB":4,"num":529,"block":0,"type":1,"notes":[]},{"LPB":4,"num":536,"block":3,"type":1,"notes":[]},{"LPB":4,"num":536,"block":1,"type":1,"notes":[]},{"LPB":4,"num":538,"block":0,"type":1,"notes":[]},{"LPB":4,"num":538,"block":2,"type":1,"notes":[]},{"LPB":4,"num":540,"block":3,"type":1,"notes":[]},{"LPB":4,"num":540,"block":0,"type":1,"notes":[]},{"LPB":4,"num":545,"block":0,"type":1,"notes":[]},{"LPB":4,"num":545,"block":1,"type":1,"notes":[]},{"LPB":4,"num":554,"block":2,"type":1,"notes":[]},{"LPB":4,"num":561,"block":3,"type":1,"notes":[]},{"LPB":4,"num":574,"block":0,"type":1,"notes":[]},{"LPB":4,"num":581,"block":0,"type":1,"notes":[]},{"LPB":4,"num":590,"block":2,"type":1,"notes":[]},{"LPB":4,"num":597,"block":2,"type":1,"notes":[]},{"LPB":4,"num":611,"block":1,"type":1,"notes":[]},{"LPB":4,"num":617,"block":3,"type":1,"notes":[]},{"LPB":4,"num":627,"block":3,"type":1,"notes":[]},{"LPB":4,"num":636,"block":2,"type":1,"notes":[]},{"LPB":4,"num":648,"block":0,"type":1,"notes":[]},{"LPB":4,"num":654,"block":1,"type":1,"notes":[]},{"LPB":4,"num":664,"block":3,"type":1,"notes":[]},{"LPB":4,"num":674,"block":2,"type":1,"notes":[]},{"LPB":4,"num":683,"block":0,"type":1,"notes":[]},{"LPB":4,"num":683,"block":3,"type":1,"notes":[]},{"LPB":4,"num":691,"block":0,"type":1,"notes":[]},{"LPB":4,"num":691,"block":1,"type":1,"notes":[]},{"LPB":4,"num":695,"block":3,"type":1,"notes":[]},{"LPB":4,"num":695,"block":2,"type":1,"notes":[]},{"LPB":4,"num":699,"block":0,"type":1,"notes":[]},{"LPB":4,"num":699,"block":1,"type":1,"notes":[]},{"LPB":4,"num":711,"block":1,"type":1,"notes":[]},{"LPB":4,"num":711,"block":2,"type":1,"notes":[]},{"LPB":4,"num":720,"block":0,"type":1,"notes":[]},{"LPB":4,"num":720,"block":3,"type":1,"notes":[]},{"LPB":4,"num":725,"block":0,"type":1,"notes":[]},{"LPB":4,"num":725,"block":2,"type":1,"notes":[]},{"LPB":4,"num":729,"block":0,"type":1,"notes":[]},{"LPB":4,"num":729,"block":1,"type":1,"notes":[]},{"LPB":4,"num":734,"block":0,"type":1,"notes":[]},{"LPB":4,"num":734,"block":2,"type":1,"notes":[]},{"LPB":4,"num":739,"block":0,"type":1,"notes":[]},{"LPB":4,"num":739,"block":3,"type":1,"notes":[]},{"LPB":4,"num":748,"block":3,"type":1,"notes":[]},{"LPB":4,"num":752,"block":2,"type":1,"notes":[]},{"LPB":4,"num":752,"block":3,"type":1,"notes":[]},{"LPB":4,"num":754,"block":1,"type":1,"notes":[]},{"LPB":4,"num":754,"block":0,"type":1,"notes":[]},{"LPB":4,"num":754,"block":3,"type":1,"notes":[]},{"LPB":4,"num":761,"block":3,"type":1,"notes":[]},{"LPB":4,"num":770,"block":0,"type":1,"notes":[]},{"LPB":4,"num":779,"block":2,"type":1,"notes":[]},{"LPB":4,"num":788,"block":1,"type":1,"notes":[]},{"LPB":4,"num":798,"block":0,"type":1,"notes":[]},{"LPB":4,"num":803,"block":0,"type":1,"notes":[]},{"LPB":4,"num":807,"block":2,"type":1,"notes":[]},{"LPB":4,"num":812,"block":2,"type":1,"notes":[]},{"LPB":4,"num":816,"block":0,"type":1,"notes":[]},{"LPB":4,"num":821,"block":0,"type":1,"notes":[]},{"LPB":4,"num":825,"block":3,"type":1,"notes":[]},{"LPB":4,"num":830,"block":3,"type":1,"notes":[]},{"LPB":4,"num":834,"block":0,"type":1,"notes":[]},{"LPB":4,"num":834,"block":1,"type":1,"notes":[]},{"LPB":4,"num":839,"block":1,"type":1,"notes":[]},{"LPB":4,"num":839,"block":2,"type":1,"notes":[]},{"LPB":4,"num":843,"block":2,"type":1,"notes":[]},{"LPB":4,"num":843,"block":3,"type":1,"notes":[]},{"LPB":4,"num":848,"block":0,"type":1,"notes":[]},{"LPB":4,"num":848,"block":2,"type":1,"notes":[]},{"LPB":4,"num":848,"block":1,"type":1,"notes":[]},{"LPB":4,"num":852,"block":0,"type":1,"notes":[]},{"LPB":4,"num":852,"block":2,"type":1,"notes":[]},{"LPB":4,"num":852,"block":3,"type":1,"notes":[]},{"LPB":4,"num":857,"block":1,"type":1,"notes":[]},{"LPB":4,"num":857,"block":2,"type":1,"notes":[]},{"LPB":4,"num":857,"block":3,"type":1,"notes":[]},{"LPB":4,"num":862,"block":0,"type":1,"notes":[]},{"LPB":4,"num":862,"block":1,"type":1,"notes":[]},{"LPB":4,"num":862,"block":3,"type":1,"notes":[]},{"LPB":4,"num":867,"block":2,"type":1,"notes":[]},{"LPB":4,"num":867,"block":3,"type":1,"notes":[]},{"LPB":4,"num":871,"block":1,"type":1,"notes":[]},{"LPB":4,"num":871,"block":2,"type":1,"notes":[]},{"LPB":4,"num":876,"block":1,"type":1,"notes":[]},{"LPB":4,"num":876,"block":0,"type":1,"notes":[]},{"LPB":4,"num":880,"block":0,"type":1,"notes":[]},{"LPB":4,"num":880,"block":1,"type":1,"notes":[]},{"LPB":4,"num":885,"block":1,"type":1,"notes":[]},{"LPB":4,"num":885,"block":2,"type":1,"notes":[]},{"LPB":4,"num":889,"block":3,"type":1,"notes":[]},{"LPB":4,"num":889,"block":2,"type":1,"notes":[]},{"LPB":4,"num":894,"block":2,"type":1,"notes":[]},{"LPB":4,"num":894,"block":3,"type":1,"notes":[]},{"LPB":4,"num":898,"block":1,"type":1,"notes":[]},{"LPB":4,"num":898,"block":2,"type":1,"notes":[]},{"LPB":4,"num":903,"block":3,"type":1,"notes":[]},{"LPB":4,"num":903,"block":0,"type":1,"notes":[]},{"LPB":4,"num":905,"block":1,"type":1,"notes":[]},{"LPB":4,"num":905,"block":2,"type":1,"notes":[]},{"LPB":4,"num":909,"block":3,"type":1,"notes":[]},{"LPB":4,"num":909,"block":0,"type":1,"notes":[]},{"LPB":4,"num":914,"block":0,"type":1,"notes":[]},{"LPB":4,"num":914,"block":3,"type":1,"notes":[]},{"LPB":4,"num":919,"block":0,"type":1,"notes":[]},{"LPB":4,"num":919,"block":2,"type":1,"notes":[]},{"LPB":4,"num":925,"block":3,"type":1,"notes":[]},{"LPB":4,"num":925,"block":1,"type":1,"notes":[]},{"LPB":4,"num":930,"block":0,"type":1,"notes":[]},{"LPB":4,"num":930,"block":1,"type":1,"notes":[]},{"LPB":4,"num":935,"block":3,"type":1,"notes":[]},{"LPB":4,"num":943,"block":1,"type":1,"notes":[]}]}